setup.py
sky_distributions/Binomialdistribution.py
sky_distributions/Gaussiandistribution.py
sky_distributions/Generaldistribution.py
sky_distributions/__init__.py
sky_distributions.egg-info/PKG-INFO
sky_distributions.egg-info/SOURCES.txt
sky_distributions.egg-info/dependency_links.txt
sky_distributions.egg-info/not-zip-safe
sky_distributions.egg-info/top_level.txt